blueqat_gk_backend
