Metadata-Version: 2.1
Name: blueqat-gk-backend
Version: 0.0.6
Summary: Blueqat backend
Home-page: https://github.com/gyu-don/blueqat-classicalbit-backend
Author: gyu-don
Author-email: takumi.kt+blueqat@gmail.com
License: Apache 2
Platform: UNKNOWN
Classifier: Programming Language :: Python :: 3
Classifier: License :: OSI Approved :: Apache Software License
